spifpy/__init__.py
spifpy/__version__.py
spifpy/images.py
spifpy/spif.py
spifpy/utils.py
spifpy/config/2DC.ini
spifpy/config/2DS.ini
spifpy/config/CIP.ini
spifpy/config/CIP25.ini
spifpy/config/CIP_grey.ini
spifpy/config/HVPS.ini
spifpy/config/PIP.ini
spifpy/config/aux_config.ini
spifpy/core/dataset.py
spifpy/input/__init__.py
spifpy/input/binary_file.py
spifpy/input/dmt_binary_file.py
spifpy/input/dmt_grey_file.py
spifpy/input/dmt_grey_mono_file.py
spifpy/input/dmt_mono_file.py
spifpy/input/input_utils.py
spifpy/input/sea.py
spifpy/input/spec_file.py
spifpy/input/tag.py
spifpy/input/twod_file.py
spifpy/input/dmt/__init__.py
spifpy/input/dmt/grey/__init__.py
spifpy/input/dmt/mono/__init__.py
spifpy/input/dmt/mono/buffer.py
spifpy/input/dmt/mono/dmt_mono_file.py
spifpy/input/dmt/mono/housekeeping.py
spifpy/input/dmt/mono/image.py
spifpy/input/spec/__init__.py
spifpy/input/spec/buffer.py
spifpy/input/spec/housekeeping.py
spifpy/input/spec/image.py
spifpy/input/spec/spec_file.py
spifpy/probes/ProbeFactory.py
spifpy/probes/__init__.py
spifpy/probes/probetypes.py
spifpy/scripts/__init__.py
spifpy/scripts/addaux.py
spifpy/scripts/copyconf.py
spifpy/scripts/cut.py
spifpy/scripts/extract.py
spifpy/scripts/extract_with_time_opts.py
spifpy-1.0.5.dist-info/LICENSE
spifpy-1.0.5.dist-info/METADATA
spifpy-1.0.5.dist-info/WHEEL
spifpy-1.0.5.dist-info/entry_points.txt
spifpy-1.0.5.dist-info/top_level.txt
spifpy-1.0.5.dist-info/RECORD
