Metadata-Version: 2.1
Name: spifpy
Version: 1.0.5
Summary: Single Particle Image Format (SPIF) data converter and interface
Home-page: https://github.com/GraupelLabs/spifpy
Author: Kenny Bala
Author-email: Kliti.Bala@nrc-cnrc.gc.ca
License: MIT
Keywords: SPIF,Converter
Classifier: Development Status :: 5 - Production/Stable
Classifier: Environment :: Console
Classifier: Intended Audience :: Science/Research
Classifier: License :: OSI Approved :: MIT License
Classifier: Natural Language :: English
Classifier: Operating System :: OS Independent
Classifier: Programming Language :: Python :: 3
Classifier: Programming Language :: Python :: 3 :: Only
Classifier: Programming Language :: Python :: 3.7
Classifier: Programming Language :: Python :: 3.8
Classifier: Programming Language :: Python :: 3.9
Classifier: Programming Language :: Python :: 3.10
Classifier: Topic :: Scientific/Engineering :: Atmospheric Science
Requires-Python: >=3.7
License-File: LICENSE
Requires-Dist: numpy
Requires-Dist: netCDF4 (>=1.5.7)
Requires-Dist: h5netcdf
Requires-Dist: xarray
Requires-Dist: tqdm
Requires-Dist: numba
Requires-Dist: joblib
Requires-Dist: scipy
Requires-Dist: click
Provides-Extra: dev
Requires-Dist: pre-commit ; extra == 'dev'
Requires-Dist: pytest (<8.0,>=7.0.0) ; extra == 'dev'
Requires-Dist: pytest-cov (<3.0,>=2.12.1) ; extra == 'dev'
